README.txt
bootstrap.py
buildout.cfg
setup.py
docs/HISTORY.txt
src/megrok/__init__.py
src/megrok.nozodb.egg-info/PKG-INFO
src/megrok.nozodb.egg-info/SOURCES.txt
src/megrok.nozodb.egg-info/dependency_links.txt
src/megrok.nozodb.egg-info/entry_points.txt
src/megrok.nozodb.egg-info/namespace_packages.txt
src/megrok.nozodb.egg-info/not-zip-safe
src/megrok.nozodb.egg-info/requires.txt
src/megrok.nozodb.egg-info/top_level.txt
src/megrok/nozodb/README.txt
src/megrok/nozodb/__init__.py
src/megrok/nozodb/components.py
src/megrok/nozodb/nozodb.py
src/megrok/nozodb/utils.py
src/megrok/nozodb/tests/__init__.py
src/megrok/nozodb/tests/test_megroknozodb.py