Metadata-Version: 1.0
Name: megrok.nozodb
Version: 0.1
Summary: This package allows you to run grok without the zodb
Home-page: http://pypi.python.org/pypi
Author: Christian Klinger
Author-email: cklinger@novareto.de
License: GPL
Keywords: grok wsgi zodb
Platform: UNKNOWN
Classifier: Programming Language :: Python
